{
  "active_lock_reason": null,
  "assignee": {
    "avatar_url": "https://avatars.githubusercontent.com/u/3246492?v=4",
    "events_url": "https://api.github.com/users/cstyan/events{/privacy}",
    "followers_url": "https://api.github.com/users/cstyan/followers",
    "following_url": "https://api.github.com/users/cstyan/following{/other_user}",
    "gists_url": "https://api.github.com/users/cstyan/gists{/gist_id}",
    "gravatar_id": "",
    "html_url": "https://github.com/cstyan",
    "id": 3246492,
    "login": "cstyan",
    "node_id": "MDQ6VXNlcjMyNDY0OTI=",
    "organizations_url": "https://api.github.com/users/cstyan/orgs",
    "received_events_url": "https://api.github.com/users/cstyan/received_events",
    "repos_url": "https://api.github.com/users/cstyan/repos",
    "site_admin": false,
    "starred_url": "https://api.github.com/users/cstyan/starred{/owner}{/repo}",
    "subscriptions_url": "https://api.github.com/users/cstyan/subscriptions",
    "type": "User",
    "url": "https://api.github.com/users/cstyan",
    "user_view_type": "public"
  },
  "assignees": [
    {
      "avatar_url": "https://avatars.githubusercontent.com/u/3246492?v=4",
      "events_url": "https://api.github.com/users/cstyan/events{/privacy}",
      "followers_url": "https://api.github.com/users/cstyan/followers",
      "following_url": "https://api.github.com/users/cstyan/following{/other_user}",
      "gists_url": "https://api.github.com/users/cstyan/gists{/gist_id}",
      "gravatar_id": "",
      "html_url": "https://github.com/cstyan",
      "id": 3246492,
      "login": "cstyan",
      "node_id": "MDQ6VXNlcjMyNDY0OTI=",
      "organizations_url": "https://api.github.com/users/cstyan/orgs",
      "received_events_url": "https://api.github.com/users/cstyan/received_events",
      "repos_url": "https://api.github.com/users/cstyan/repos",
      "site_admin": false,
      "starred_url": "https://api.github.com/users/cstyan/starred{/owner}{/repo}",
      "subscriptions_url": "https://api.github.com/users/cstyan/subscriptions",
      "type": "User",
      "url": "https://api.github.com/users/cstyan",
      "user_view_type": "public"
    }
  ],
  "author_association": "MEMBER",
  "body": "The flake here had two causes:\r\n1. related to usage of time.Now() in MustWaitForProvisionersAvailable and \r\n2. the fact that UpdateProvisionerLastSeenAt can not use a time that is further in the past than the current LastSeenAt time\r\n\r\nPreviously the test here was calling `coderdtest.MustWaitForProvisionersAvailable` which was using `time.Now` rather than the next tick time like the real `hasProvisionersAvailable` function does. Additionally, when using `UpdateProvisionerLastSeenAt` the underlying db query enforces that the time we're trying to set `LastSeenAt` to cannot be older than the current value.\r\n\r\nI was able to reliably reproduce the flake by executing both the `UpdateProvisionerLastSeenAt` call and `tickCh <- next` in their own goroutines, the former with a small sleep to reliably ensure we'd trigger the autobuild before we set the `LastSeenAt` time. That's when I also noticed that `coderdtest.MustWaitForProvisionersAvailable` was using `time.Now` instead of the tick time. When I updated that function to take in a tick time + added a 2nd call to `UpdateProvisionerLastSeenAt` to set an original non-stale time, we could then never get the test to pass because the later call to set the stale time would not actually modify `LastSeenAt`. On top of that, calling the provisioner daemons closer in the middle of the function doesn't really do anything of value in this test.\r\n\r\n**The fix for the flake is to keep the go routines, ensuring there would be a flake if there was not a relevant fix, but to include the fix which is to ensure that we explicitly wait for the provisioner to be stale before passing the time to `tickCh`.**",
  "closed_at": "2025-08-28T19:07:50Z",
  "closed_by": {
    "avatar_url": "https://avatars.githubusercontent.com/u/3246492?v=4",
    "events_url": "https://api.github.com/users/cstyan/events{/privacy}",
    "followers_url": "https://api.github.com/users/cstyan/followers",
    "following_url": "https://api.github.com/users/cstyan/following{/other_user}",
    "gists_url": "https://api.github.com/users/cstyan/gists{/gist_id}",
    "gravatar_id": "",
    "html_url": "https://github.com/cstyan",
    "id": 3246492,
    "login": "cstyan",
    "node_id": "MDQ6VXNlcjMyNDY0OTI=",
    "organizations_url": "https://api.github.com/users/cstyan/orgs",
    "received_events_url": "https://api.github.com/users/cstyan/received_events",
    "repos_url": "https://api.github.com/users/cstyan/repos",
    "site_admin": false,
    "starred_url": "https://api.github.com/users/cstyan/starred{/owner}{/repo}",
    "subscriptions_url": "https://api.github.com/users/cstyan/subscriptions",
    "type": "User",
    "url": "https://api.github.com/users/cstyan",
    "user_view_type": "public"
  },
  "comments": 0,
  "comments_url": "https://api.github.com/repos/coder/coder/issues/19478/comments",
  "created_at": "2025-08-21T21:10:35Z",
  "draft": false,
  "events_url": "https://api.github.com/repos/coder/coder/issues/19478/events",
  "html_url": "https://github.com/coder/coder/pull/19478",
  "id": 3343204857,
  "issue_field_values": [],
  "labels": [],
  "labels_url": "https://api.github.com/repos/coder/coder/issues/19478/labels{/name}",
  "locked": true,
  "milestone": null,
  "node_id": "PR_kwDOGkVX1s6kw9Wa",
  "number": 19478,
  "performed_via_github_app": null,
  "pull_request": {
    "diff_url": "https://github.com/coder/coder/pull/19478.diff",
    "html_url": "https://github.com/coder/coder/pull/19478",
    "merged_at": "2025-08-28T19:07:50Z",
    "patch_url": "https://github.com/coder/coder/pull/19478.patch",
    "url": "https://api.github.com/repos/coder/coder/pulls/19478"
  },
  "reactions": {
    "+1": 0,
    "-1": 0,
    "confused": 0,
    "eyes": 0,
    "heart": 0,
    "hooray": 0,
    "laugh": 0,
    "rocket": 0,
    "total_count": 0,
    "url": "https://api.github.com/repos/coder/coder/issues/19478/reactions"
  },
  "repository_url": "https://api.github.com/repos/coder/coder",
  "state": "closed",
  "state_reason": null,
  "timeline_url": "https://api.github.com/repos/coder/coder/issues/19478/timeline",
  "title": "fix: fix flake in TestExecutorAutostartSkipsWhenNoProvisionersAvailable",
  "type": null,
  "updated_at": "2025-08-28T19:07:59Z",
  "url": "https://api.github.com/repos/coder/coder/issues/19478",
  "user": {
    "avatar_url": "https://avatars.githubusercontent.com/u/3246492?v=4",
    "events_url": "https://api.github.com/users/cstyan/events{/privacy}",
    "followers_url": "https://api.github.com/users/cstyan/followers",
    "following_url": "https://api.github.com/users/cstyan/following{/other_user}",
    "gists_url": "https://api.github.com/users/cstyan/gists{/gist_id}",
    "gravatar_id": "",
    "html_url": "https://github.com/cstyan",
    "id": 3246492,
    "login": "cstyan",
    "node_id": "MDQ6VXNlcjMyNDY0OTI=",
    "organizations_url": "https://api.github.com/users/cstyan/orgs",
    "received_events_url": "https://api.github.com/users/cstyan/received_events",
    "repos_url": "https://api.github.com/users/cstyan/repos",
    "site_admin": false,
    "starred_url": "https://api.github.com/users/cstyan/starred{/owner}{/repo}",
    "subscriptions_url": "https://api.github.com/users/cstyan/subscriptions",
    "type": "User",
    "url": "https://api.github.com/users/cstyan",
    "user_view_type": "public"
  }
}