{
  "active_lock_reason": null,
  "assignee": {
    "avatar_url": "https://avatars.githubusercontent.com/u/5446298?v=4",
    "events_url": "https://api.github.com/users/Emyrk/events{/privacy}",
    "followers_url": "https://api.github.com/users/Emyrk/followers",
    "following_url": "https://api.github.com/users/Emyrk/following{/other_user}",
    "gists_url": "https://api.github.com/users/Emyrk/gists{/gist_id}",
    "gravatar_id": "",
    "html_url": "https://github.com/Emyrk",
    "id": 5446298,
    "login": "Emyrk",
    "node_id": "MDQ6VXNlcjU0NDYyOTg=",
    "organizations_url": "https://api.github.com/users/Emyrk/orgs",
    "received_events_url": "https://api.github.com/users/Emyrk/received_events",
    "repos_url": "https://api.github.com/users/Emyrk/repos",
    "site_admin": false,
    "starred_url": "https://api.github.com/users/Emyrk/starred{/owner}{/repo}",
    "subscriptions_url": "https://api.github.com/users/Emyrk/subscriptions",
    "type": "User",
    "url": "https://api.github.com/users/Emyrk",
    "user_view_type": "public"
  },
  "assignees": [
    {
      "avatar_url": "https://avatars.githubusercontent.com/u/5446298?v=4",
      "events_url": "https://api.github.com/users/Emyrk/events{/privacy}",
      "followers_url": "https://api.github.com/users/Emyrk/followers",
      "following_url": "https://api.github.com/users/Emyrk/following{/other_user}",
      "gists_url": "https://api.github.com/users/Emyrk/gists{/gist_id}",
      "gravatar_id": "",
      "html_url": "https://github.com/Emyrk",
      "id": 5446298,
      "login": "Emyrk",
      "node_id": "MDQ6VXNlcjU0NDYyOTg=",
      "organizations_url": "https://api.github.com/users/Emyrk/orgs",
      "received_events_url": "https://api.github.com/users/Emyrk/received_events",
      "repos_url": "https://api.github.com/users/Emyrk/repos",
      "site_admin": false,
      "starred_url": "https://api.github.com/users/Emyrk/starred{/owner}{/repo}",
      "subscriptions_url": "https://api.github.com/users/Emyrk/subscriptions",
      "type": "User",
      "url": "https://api.github.com/users/Emyrk",
      "user_view_type": "public"
    }
  ],
  "author_association": "MEMBER",
  "body": "https://github.com/coder/coder/runs/19666833200\r\n\r\nTest times out after 10 minutes due to a deadlock in shutting down the agent\r\n\r\n```\r\ngoroutine 2555 [semacquire, 9 minutes]:\r\nsync.runtime_Semacquire(0xc0006ae1b0?)\r\n\t/opt/hostedtoolcache/go/1.21.5/x64/src/runtime/sema.go:62 +0x25\r\nsync.(*WaitGroup).Wait(0xc0006ae1a8)\r\n\t/opt/hostedtoolcache/go/1.21.5/x64/src/sync/waitgroup.go:116 +0xa5\r\ngithub.com/coder/coder/v2/agent/agentscripts.(*Runner).Close(0xc0006ae100)\r\n\t/home/runner/actions-runner/_work/coder/coder/agent/agentscripts/agentscripts.go:320 +0x19e\r\ngithub.com/coder/coder/v2/agent.(*agent).Close(0xc004a0b200)\r\n\t/home/runner/actions-runner/_work/coder/coder/agent/agent.go:1498 +0x439\r\ngithub.com/coder/coder/v2/agent_test.TestAgent_WriteVSCodeConfigs(0xc005b456c0)\r\n\t/home/runner/actions-runner/_work/coder/coder/agent/agent_test.go:1870 +0x160a\r\ntesting.tRunner(0xc005b456c0, 0x27ceba0)\r\n\t/opt/hostedtoolcache/go/1.21.5/x64/src/testing/testing.go:1595 +0x262\r\ncreated by testing.(*T).Run in goroutine 1\r\n\t/opt/hostedtoolcache/go/1.21.5/x64/src/testing/testing.go:1648 +0x846\r\n```",
  "closed_at": "2023-12-18T15:26:41Z",
  "closed_by": {
    "avatar_url": "https://avatars.githubusercontent.com/u/5446298?v=4",
    "events_url": "https://api.github.com/users/Emyrk/events{/privacy}",
    "followers_url": "https://api.github.com/users/Emyrk/followers",
    "following_url": "https://api.github.com/users/Emyrk/following{/other_user}",
    "gists_url": "https://api.github.com/users/Emyrk/gists{/gist_id}",
    "gravatar_id": "",
    "html_url": "https://github.com/Emyrk",
    "id": 5446298,
    "login": "Emyrk",
    "node_id": "MDQ6VXNlcjU0NDYyOTg=",
    "organizations_url": "https://api.github.com/users/Emyrk/orgs",
    "received_events_url": "https://api.github.com/users/Emyrk/received_events",
    "repos_url": "https://api.github.com/users/Emyrk/repos",
    "site_admin": false,
    "starred_url": "https://api.github.com/users/Emyrk/starred{/owner}{/repo}",
    "subscriptions_url": "https://api.github.com/users/Emyrk/subscriptions",
    "type": "User",
    "url": "https://api.github.com/users/Emyrk",
    "user_view_type": "public"
  },
  "comments": 1,
  "comments_url": "https://api.github.com/repos/coder/coder/issues/11226/comments",
  "created_at": "2023-12-15T07:29:51Z",
  "events_url": "https://api.github.com/repos/coder/coder/issues/11226/events",
  "html_url": "https://github.com/coder/coder/issues/11226",
  "id": 2043056793,
  "issue_dependencies_summary": {
    "blocked_by": 0,
    "blocking": 0,
    "total_blocked_by": 0,
    "total_blocking": 0
  },
  "issue_field_values": [],
  "labels": [
    {
      "color": "FFBD0C",
      "default": false,
      "description": "Bugs that confuse, annoy, or are purely cosmetic",
      "id": 5135465564,
      "name": "s3",
      "node_id": "LA_kwDOGkVX1s8AAAABMhj8XA",
      "url": "https://api.github.com/repos/coder/coder/labels/s3"
    }
  ],
  "labels_url": "https://api.github.com/repos/coder/coder/issues/11226/labels{/name}",
  "locked": false,
  "milestone": null,
  "node_id": "I_kwDOGkVX1s55xpKZ",
  "number": 11226,
  "performed_via_github_app": null,
  "pinned_comment": null,
  "reactions": {
    "+1": 0,
    "-1": 0,
    "confused": 0,
    "eyes": 0,
    "heart": 0,
    "hooray": 0,
    "laugh": 0,
    "rocket": 0,
    "total_count": 0,
    "url": "https://api.github.com/repos/coder/coder/issues/11226/reactions"
  },
  "repository_url": "https://api.github.com/repos/coder/coder",
  "state": "closed",
  "state_reason": "completed",
  "sub_issues_summary": {
    "completed": 0,
    "percent_completed": 0,
    "total": 0
  },
  "timeline_url": "https://api.github.com/repos/coder/coder/issues/11226/timeline",
  "title": "flake: TestAgent_WriteVSCodeConfigs",
  "type": null,
  "updated_at": "2023-12-18T15:26:43Z",
  "url": "https://api.github.com/repos/coder/coder/issues/11226",
  "user": {
    "avatar_url": "https://avatars.githubusercontent.com/u/5375600?v=4",
    "events_url": "https://api.github.com/users/spikecurtis/events{/privacy}",
    "followers_url": "https://api.github.com/users/spikecurtis/followers",
    "following_url": "https://api.github.com/users/spikecurtis/following{/other_user}",
    "gists_url": "https://api.github.com/users/spikecurtis/gists{/gist_id}",
    "gravatar_id": "",
    "html_url": "https://github.com/spikecurtis",
    "id": 5375600,
    "login": "spikecurtis",
    "node_id": "MDQ6VXNlcjUzNzU2MDA=",
    "organizations_url": "https://api.github.com/users/spikecurtis/orgs",
    "received_events_url": "https://api.github.com/users/spikecurtis/received_events",
    "repos_url": "https://api.github.com/users/spikecurtis/repos",
    "site_admin": false,
    "starred_url": "https://api.github.com/users/spikecurtis/starred{/owner}{/repo}",
    "subscriptions_url": "https://api.github.com/users/spikecurtis/subscriptions",
    "type": "User",
    "url": "https://api.github.com/users/spikecurtis",
    "user_view_type": "public"
  }
}